clldlucl/__init__.py
clldlucl/__main__.py
clldlucl/cdstar.py
clldlucl/commands.py
clldlucl/scaffolds/__init__.py
clldlucl/scaffolds/clld_app/.gitignore
clldlucl/scaffolds/clld_app/CONTRIBUTING.md_tmpl
clldlucl/scaffolds/clld_app/MANIFEST.in_tmpl
clldlucl/scaffolds/clld_app/README.md
clldlucl/scaffolds/clld_app/alembic.ini_tmpl
clldlucl/scaffolds/clld_app/development.ini_tmpl
clldlucl/scaffolds/clld_app/setup.cfg_tmpl
clldlucl/scaffolds/clld_app/tox.ini
clldlucl/scaffolds/clld_app/+package+/__init__.py_tmpl
clldlucl/scaffolds/clld_app/+package+/adapters.py_tmpl
clldlucl/scaffolds/clld_app/+package+/appconf.ini_tmpl
clldlucl/scaffolds/clld_app/+package+/assets.py_tmpl
clldlucl/scaffolds/clld_app/+package+/datatables.py_tmpl
clldlucl/scaffolds/clld_app/+package+/interfaces.py
clldlucl/scaffolds/clld_app/+package+/maps.py_tmpl
clldlucl/scaffolds/clld_app/+package+/models.py_tmpl
clldlucl/scaffolds/clld_app/+package+/util.py
clldlucl/scaffolds/clld_app/+package+/views.py_tmpl
clldlucl/scaffolds/clld_app/+package+/locale/+package+.pot
clldlucl/scaffolds/clld_app/+package+/scripts/__init__.py
clldlucl/scaffolds/clld_app/+package+/scripts/initializedb.py_tmpl
clldlucl/scaffolds/clld_app/+package+/static/project.css
clldlucl/scaffolds/clld_app/+package+/static/project.js
clldlucl/scaffolds/clld_app/+package+/static/download/.gitignore
clldlucl/scaffolds/clld_app/+package+/templates/+package+.mako_tmpl
clldlucl/scaffolds/clld_app/+package+/templates/dataset/detail_html.mako_tmpl
clldlucl/scaffolds/clld_app/+package+/tests/__init__.py
clldlucl/scaffolds/clld_app/data/README.txt
clldlucl/scaffolds/clld_app/migrations/env.py
clldlucl/scaffolds/clld_app/migrations/script.py.mako
clldlucl/scaffolds/clld_app/tests/conftest.py_tmpl
clldlucl/scaffolds/clld_app/tests/test_functional.py
clldlucl/scaffolds/clld_app/tests/test_scripts.py_tmpl
clldlucl/scaffolds/clld_app/tests/test_selenium.py
clldlucl/static/lucl.png
clldlucl/static/minerva.png
clldlucl/templates/clldlucl_util.mako
clldlucl-3.0.0b2.dist-info/LICENSE
clldlucl-3.0.0b2.dist-info/METADATA
clldlucl-3.0.0b2.dist-info/WHEEL
clldlucl-3.0.0b2.dist-info/entry_points.txt
clldlucl-3.0.0b2.dist-info/top_level.txt
clldlucl-3.0.0b2.dist-info/RECORD
